pggm_datalab_utils/db.py
pggm_datalab_utils/flatten.py
pggm_datalab_utils-2.19.dist-info/METADATA
pggm_datalab_utils-2.19.dist-info/WHEEL
pggm_datalab_utils-2.19.dist-info/RECORD
