Metadata-Version: 2.4
Name: pggm-datalab-utils
Version: 2.19
Summary: Utilities created and used by the Datalab of PGGM
Author-email: Rik de Kort <rik.de.kort@pggm.nl>
Requires-Python: <4.0,>=3.9
Requires-Dist: azure-identity<2.0.0,>=1.15.0
Requires-Dist: pyodbc>=4.0.39
